wikiscraper/__init__.py
wikiscraper/examples.py
wikiscraper/test_wiki.py
wikiscraper-1.1.9.dist-info/LICENSE.md
wikiscraper-1.1.9.dist-info/METADATA
wikiscraper-1.1.9.dist-info/WHEEL
wikiscraper-1.1.9.dist-info/top_level.txt
wikiscraper-1.1.9.dist-info/RECORD
