Metadata-Version: 2.1
Name: wikiscraper
Version: 1.1.9
Summary: Easy scraper that extracts data from Wikipedia articles thanks to its URL slug
Home-page: https://github.com/Alexandre333/wikiscraper
Author: Alexandre Meyer
Author-email: contact@alexandremeyer.fr
Keywords: python,web scraping,wikipedia,slug
Classifier: Development Status :: 5 - Production/Stable
Classifier: Intended Audience :: Developers
Classifier: Programming Language :: Python :: 3
Classifier: Operating System :: Unix
Classifier: Operating System :: MacOS :: MacOS X
Classifier: Operating System :: Microsoft :: Windows
License-File: LICENSE.md
Requires-Dist: requests
Requires-Dist: beautifulsoup4
